solara_assets/__init__.py
solara_assets-0.7.0.data/data/share/solara/cdn/@widgetti/solara-milkdown@6.3.0/.bumpversion.cfg
solara_assets-0.7.0.data/data/share/solara/cdn/@widgetti/solara-milkdown@6.3.0/package.json
solara_assets-0.7.0.data/data/share/solara/cdn/@widgetti/solara-milkdown@6.3.0/solara-sql.db
solara_assets-0.7.0.data/data/share/solara/cdn/@widgetti/solara-milkdown@6.3.0/webpack.config.js
solara_assets-0.7.0.data/data/share/solara/cdn/@widgetti/solara-milkdown@6.3.0/.idea/misc.xml
solara_assets-0.7.0.data/data/share/solara/cdn/@widgetti/solara-milkdown@6.3.0/.idea/modules.xml
solara_assets-0.7.0.data/data/share/solara/cdn/@widgetti/solara-milkdown@6.3.0/.idea/solara-markdown-js.iml
solara_assets-0.7.0.data/data/share/solara/cdn/@widgetti/solara-milkdown@6.3.0/src/index.js
solara_assets-0.7.0.data/data/share/solara/cdn/@widgetti/solara-milkdown@6.3.0/states/5f3d1ec2-0e51-4272-9b31-b2908ce4f971.pickle
solara_assets-0.7.0.data/data/share/solara/cdn/@widgetti/solara-milkdown@6.3.0/states/6faf3bd3-d60a-49eb-b763-03383eff8f57.pickle
solara_assets-0.7.0.data/data/share/solara/cdn/@widgetti/solara-vuetify-app@1.0.0/package.json
solara_assets-0.7.0.data/data/share/solara/cdn/@widgetti/solara-vuetify-app@1.0.0/webpack.config.js
solara_assets-0.7.0.data/data/share/solara/cdn/@widgetti/solara-vuetify-app@1.0.0/src/solara-vuetify-app.js
solara_assets-0.7.0.data/data/share/solara/cdn/@widgetti/vue-grid-layout@2.3.13-alpha.2/.browserslistrc
solara_assets-0.7.0.data/data/share/solara/cdn/@widgetti/vue-grid-layout@2.3.13-alpha.2/.eslintrc.js
solara_assets-0.7.0.data/data/share/solara/cdn/@widgetti/vue-grid-layout@2.3.13-alpha.2/LICENSE
solara_assets-0.7.0.data/data/share/solara/cdn/@widgetti/vue-grid-layout@2.3.13-alpha.2/README-zh_CN.md
solara_assets-0.7.0.data/data/share/solara/cdn/@widgetti/vue-grid-layout@2.3.13-alpha.2/README.md
solara_assets-0.7.0.data/data/share/solara/cdn/@widgetti/vue-grid-layout@2.3.13-alpha.2/babel.config.js
solara_assets-0.7.0.dist-info/METADATA
solara_assets-0.7.0.dist-info/WHEEL
solara_assets-0.7.0.dist-info/licenses/LICENSE
solara_assets-0.7.0.dist-info/RECORD
