Metadata-Version: 2.1
Name: solara-assets
Version: 0.7.0
Project-URL: Home, https://www.github.com/widgetti/solara
Author-email: "Maarten A. Breddels" <maartenbreddels@gmail.com>
License: The MIT License (MIT)
Classifier: License :: OSI Approved :: MIT License
Requires-Dist: solara
